prompt_args/__init__.py
prompt_args/prompt_args.py
prompt_args/__pycache__/__init__.cpython-311.pyc
prompt_args/__pycache__/prompt_args.cpython-311.pyc
prompt_args-1.0.1.dist-info/LICENSE
prompt_args-1.0.1.dist-info/METADATA
prompt_args-1.0.1.dist-info/WHEEL
prompt_args-1.0.1.dist-info/top_level.txt
prompt_args-1.0.1.dist-info/RECORD
