Metadata-Version: 2.1
Name: prompt-args
Version: 1.0.1
Summary: Decorator to prompt input for missing arguments.
Home-page: https://github.com/justengel/prompt_args
Download-URL: https://github.com/justengel/prompt_args/archive/refs/tags/v1.0.1.tar.gz
Author: Justin Engel
Author-email: jtengel08@gmail.com
License: Proprietary
Keywords: prompt input args kwargs decorator
Platform: any
Classifier: Programming Language :: Python
Classifier: Programming Language :: Python :: 3
Classifier: Operating System :: OS Independent
License-File: LICENSE
